celeste_xai/__init__.py
celeste_xai/py.typed
celeste_xai/responses/__init__.py
celeste_xai/responses/client.py
celeste_xai/responses/config.py
celeste_xai/responses/parameters.py
celeste_xai/responses/streaming.py
celeste_xai-0.3.6.dist-info/METADATA
celeste_xai-0.3.6.dist-info/WHEEL
celeste_xai-0.3.6.dist-info/RECORD
